setup.py
distributions_outlierd/Binomialdistribution.py
distributions_outlierd/Gaussiandistribution.py
distributions_outlierd/Generaldistribution.py
distributions_outlierd/__init__.py
distributions_outlierd.egg-info/PKG-INFO
distributions_outlierd.egg-info/SOURCES.txt
distributions_outlierd.egg-info/dependency_links.txt
distributions_outlierd.egg-info/not-zip-safe
distributions_outlierd.egg-info/top_level.txt