Metadata-Version: 1.0
Name: distributions-outlierd
Version: 0.1
Summary: Gaussian distributions
Home-page: UNKNOWN
Author: Deivid
Author-email: UNKNOWN
License: UNKNOWN
Platform: UNKNOWN
